{
  "type": "minecraft:gift",
  "pools": [
    {
      "rolls": 1,
      "entries": [
        {
          "type": "minecraft:loot_table",
          "name": "q_craft:puzzle_box_hard/categories/tools/iron",
          "weight": 5,
          "functions": [
            {
              "function": "minecraft:enchant_with_levels",
              "levels": {
                "min": 20.0,
                "max": 35.0,
                "type": "minecraft:uniform"
              }
            }
          ]
        },
        {
          "type": "minecraft:loot_table",
          "name": "q_craft:puzzle_box_hard/categories/tools/diamond",
          "weight": 3,
          "functions": [
            {
              "function": "minecraft:enchant_with_levels",
              "levels": {
                "min": 10.0,
                "max": 20.0,
                "type": "minecraft:uniform"
              }
            }
          ]
        },
        {
          "type": "minecraft:loot_table",
          "name": "q_craft:puzzle_box_hard/categories/tools/netherite",
          "weight": 1,
          "functions": [
            {
              "function": "minecraft:enchant_with_levels",
              "levels": {
                "min": 10.0,
                "max": 20.0,
                "type": "minecraft:uniform"
              }
            }
          ]
        },
        {
          "type": "minecraft:loot_table",
          "name": "q_craft:puzzle_box_hard/categories/tools/combat",
          "weight": 1,
          "functions": [
            {
              "function": "minecraft:enchant_with_levels",
              "levels": {
                "min": 15.0,
                "max": 30.0,
                "type": "minecraft:uniform"
              }
            }
          ]
        }
      ]
    }
  ]
}